aws_wort_des_tages/__init__.py
aws_wort_des_tages/lambda_function.py
aws_wort_des_tages-0.0.2.dist-info/METADATA
aws_wort_des_tages-0.0.2.dist-info/WHEEL
aws_wort_des_tages-0.0.2.dist-info/top_level.txt
aws_wort_des_tages-0.0.2.dist-info/RECORD
