Metadata-Version: 2.4
Name: aws-wort-des-tages
Version: 0.0.2
Summary: A serverless German vocabulary app that picks a fresh word each day, gets Generative AI to write example sentences, and emails it to subscribers.
Author-email: Mengni Zhang <monicamengni@gmail.com>
License: MIT
Keywords: German,vocabulary,learn German
Classifier: Programming Language :: Python :: 3
Classifier: Programming Language :: Python :: 3.10
Classifier: Programming Language :: Python :: 3.11
Classifier: Programming Language :: Python :: 3.12
Classifier: Programming Language :: Python :: 3.13
Requires-Python: >=3.10
Requires-Dist: boto3
Requires-Dist: importlib-metadata; python_version < "3.12"
Provides-Extra: test
Requires-Dist: pytest; extra == "test"
Requires-Dist: pytest-cov; extra == "test"
Provides-Extra: release
Requires-Dist: build; extra == "release"
Requires-Dist: twine; extra == "release"
Provides-Extra: static-code-qa
Requires-Dist: pre-commit; extra == "static-code-qa"
Provides-Extra: dev
Requires-Dist: aws-wort-des-tages[release,static-code-qa,test]; extra == "dev"
